chapter_3/3_3_fsm_prob.sv
module fsm_prob_b (
    input  logic clk,
    rstn,
    i,
    j,
    output logic x,
    y
);
  logic [1:0] st_out;

  enum logic [1:0] {
    A,
    B,
    C,
    D
  } state;
  always_ff @(posedge clk, negedge rstn) begin
    if (~rstn) state <= A;
    else begin
      case (state)
        A: state <= i ? B : A;
        B: state <= i ? C : D;
        C: state <= i ? B : j ? C : D;
        D: state <= i ? D : j ? C : A;
        default: state <= A;
      endcase
    end
  end
  always_comb begin
    unique case (state)
      A: st_out = 2'b11;
      B: st_out = 2'b01;
      C: st_out = 2'b10;
      D: st_out = 2'b10;

    endcase
  end
  assign {x, y} = st_out;

endmodule


module tb_fsm_prob_b;
  logic clk, rstn, i, j, x, y;

  fsm_prob_b mut (.*);


  initial begin

    clk  = 0;
    rstn = 0;
    #1 rstn <= 1;
    forever #5 clk = ~clk;

  end
  always @(negedge clk)
    $display(
        $time, "  ij = %b%b, xy = %b%b", i, j, x, y
    );  //negedge to print the corrent state io
  initial begin
    i <= 1;
    j <= 1;


    @(posedge clk);  // a 2 b
    #2
      assert ({x, y} == 2'b01)
      else $display("failed: expected: 01 ");
    j <= 0;
    @(posedge clk);  // b 2 d
    #2
      assert ({x, y} == 2'b10)
      else $display("failed: expected: 10 ");
    i <= 0;
    j <= 1;
    @(posedge clk);  // d 2 c
    #2
      assert ({x, y} == 2'b10)
      else $display("failed: expected: 10 ");

    @(posedge clk);  // c 2 c
    #2
      assert ({x, y} == 2'b10)
      else $display("failed: expected: 10 ");
    j <= 0;
    @(posedge clk);  // c 2 d
    #2
      assert ({x, y} == 2'b10)
      else $display("failed: expected: 10 ");
    i <= 1;
    @(posedge clk);  // d 2 d
    #2
      assert ({x, y} == 2'b10)
      else $display("failed: expected: 10 ");
    i <= 0;
    @(posedge clk);  // d 2 a
    #2
      assert ({x, y} == 2'b11)
      else $display("failed: expected: 11 ");
    @(posedge clk);  // a 2 a

    #2
      assert ({x, y} == 2'b11)
      else $display("failed: expected: 11 ");

    #2 $finish;


  end

endmodule

chapter_7_testbench_introduction/7_3_implicit_tb_3_3.sv

module top73;
  logic clk, rstn, i, j, x, y;

  fsm_prob_b dut (.*);
  tb3_3 tb (.*);

  initial begin
    $monitor($time, " current state: %b, input: ij %b%b output: xy = %b%b", dut.state, i, j, x, y);
    $dumpfile("top73.vcd");
    $dumpvars(0, top73);
    clk  = 0;
    rstn = 0;
    rstn <= #1 1;
    forever #5 clk = ~clk;
  end
endmodule




module tb3_3 (
    input  logic clk,
    output logic i,
    j
);
  initial begin
    i = 1;
    j = 0;
    @(posedge clk);
    @(posedge clk);
    @(posedge clk);
    @(posedge clk);
    i = 0;
    j = 1;
    @(posedge clk);
    @(posedge clk);
    @(posedge clk);
    j = 0;
    @(posedge clk);
    i = 1;
    @(posedge clk);
    i = 0;
    @(posedge clk);
    @(posedge clk);
    @(posedge clk);
    $finish;
  end

endmodule

chapter_7_testbench_introduction/top73.vcd
$date
	Tue Feb  4 16:07:30 2025
$end
$version
	Icarus Verilog
$end
$timescale
	1s
$end
$scope module top73 $end
$var wire 1 ! y $end
$var wire 1 " x $end
$var wire 1 # j $end
$var wire 1 $ i $end
$var reg 1 % clk $end
$var reg 1 & rstn $end
$scope module dut $end
$var wire 1 % clk $end
$var wire 1 & rstn $end
$var wire 1 ! y $end
$var wire 1 " x $end
$var wire 1 # j $end
$var wire 1 $ i $end
$var reg 2 ' st_out [1:0] $end
$var reg 2 ( state [1:0] $end
$upscope $end
$scope module tb $end
$var wire 1 % clk $end
$var reg 1 $ i $end
$var reg 1 # j $end
$upscope $end
$upscope $end
$enddefinitions $end
$comment Show the parameter values. $end
$dumpall
$end
#0
$dumpvars
b0 (
b11 '
0&
0%
1$
0#
1"
1!
$end
#1
1&
#5
0"
b1 '
b1 (
1%
#10
0%
#15
1"
0!
b10 '
b10 (
1%
#20
0%
#25
0"
1!
b1 '
b1 (
1%
#30
0%
#35
1"
0!
b10 '
b11 (
1#
0$
1%
#40
0%
#45
b10 (
1%
#50
0%
#55
1%
#60
0%
#65
b11 (
0#
1%
#70
0%
#75
1$
1%
#80
0%
#85
1!
b11 '
b0 (
0$
1%
