chapter_3_FSM/3_2_fsm_prob.sv
module fsm_prob_a (
    input  logic clk,
    rstn,
    i,
    j,
    output logic x,
    y
);
  logic [1:0] st_out;

  enum logic [1:0] {
    A,
    B,
    C,
    D
  } state;
  always_ff @(posedge clk, negedge rstn) begin
    if (~rstn) state <= A;
    else begin
      case (state)
        A: state <= i ? B : A;
        B: state <= j ? C : D;
        C: state <= i ? B : j ? C : D;
        D: state <= i ? D : j ? C : A;
        default: state <= A;
      endcase
    end
  end
  always_comb begin
    case (state)
      A: st_out = i ? 2'b11 : 2'b10;
      B: st_out = j ? 2'b01 : 2'b10;
      C: st_out = i ? 2'b0 : j ? 2'b10 : 2'b11;
      D: st_out = i ? 2'b0 : j ? 2'b10 : 2'b00;
      default: st_out = 2'b00;
    endcase
  end
  assign x = st_out[1], y = st_out[0];

endmodule

chapter_7_testbench_introduction/7_2_implicit_tb_for_3_2.sv
module top72;

logic clk, rstn,i,j,x,y;
// logic clk;
// logic rstn;
// logic i;
// logic j;
// logic x;
// logic y;

fsm_prob_a dut(.*);
tb3_2 tb(.*);

initial begin
    $monitor("current state: %b, output: xy = %b%b", dut.state,x,y);
    $dumpfile("top72.vcd");
    $dumpvars(0, top72);
    clk =0;
    rstn =0;
    rstn <= #1  1;
    forever #5 clk = ~clk;
    
end
endmodule


module tb3_2(input logic clk, output logic i,j);

initial begin
    $display( "start tb3_2");
    i =0;
    j=0;
    @(posedge clk);
    i=1;
    @(posedge clk);
    j=1;
    @(posedge clk);
    i=0;
    @(posedge clk);
    i=1;
    @(posedge clk);
    j=0;
    @(posedge clk);
    @(posedge clk);
    i=0;
    j=1;
    @(posedge clk);
    j=0;
    @(posedge clk);
    i=0;
    @(posedge clk);
    #1 $finish;
end  

endmodule

chapter_7_testbench_introduction/top72.vcd
$date
	Mon Feb  3 09:37:40 2025
$end
$version
	Icarus Verilog
$end
$timescale
	1s
$end
$scope module top72 $end
$var wire 1 ! y $end
$var wire 1 " x $end
$var wire 1 # j $end
$var wire 1 $ i $end
$var reg 1 % clk $end
$var reg 1 & rstn $end
$scope module dut $end
$var wire 1 % clk $end
$var wire 1 & rstn $end
$var wire 1 ! y $end
$var wire 1 " x $end
$var wire 1 # j $end
$var wire 1 $ i $end
$var reg 2 ' st_out [1:0] $end
$var reg 2 ( state [1:0] $end
$upscope $end
$scope module tb $end
$var wire 1 % clk $end
$var reg 1 $ i $end
$var reg 1 # j $end
$upscope $end
$upscope $end
$enddefinitions $end
$comment Show the parameter values. $end
$dumpall
$end
#0
$dumpvars
b0 (
b10 '
0&
0%
0$
0#
1"
0!
$end
#1
1&
#5
b1 (
0!
b10 '
1$
1%
#10
0%
#15
b10 (
0"
0!
b0 '
1#
1%
#20
0%
#25
1"
b10 '
0$
1%
#30
0%
#35
1!
b1 (
0"
b1 '
1$
1%
#40
0%
#45
b11 (
0"
0!
b0 '
0#
1%
#50
0%
#55
1%
#60
0%
#65
b10 (
1"
b10 '
1#
0$
1%
#70
0%
#75
0"
b11 (
0!
b0 '
0#
1%
#80
0%
#85
1"
b10 '
b0 (
1%
